codex_resume/__init__.py
codex_resume/__main__.py
codex_resume/app.py
codex_resume/config.py
codex_resume/sessions.py
codex_resume-0.4.2.dist-info/METADATA
codex_resume-0.4.2.dist-info/WHEEL
codex_resume-0.4.2.dist-info/entry_points.txt
codex_resume-0.4.2.dist-info/top_level.txt
codex_resume-0.4.2.dist-info/RECORD
