Metadata-Version: 2.4
Name: codex-resume
Version: 0.4.2
Summary: Textual-based TUI to browse and resume Codex CLI sessions
Author: darvell
License: MIT
Project-URL: Homepage, https://github.com/darvell/codex-resume
Project-URL: Repository, https://github.com/darvell/codex-resume
Project-URL: Issues, https://github.com/darvell/codex-resume/issues
Keywords: codex,tui,cli,productivity
Classifier: Development Status :: 4 - Beta
Classifier: Environment :: Console
Classifier: Intended Audience :: Developers
Classifier: License :: OSI Approved :: MIT License
Classifier: Operating System :: OS Independent
Classifier: Programming Language :: Python
Classifier: Programming Language :: Python :: 3
Classifier: Programming Language :: Python :: 3.9
Classifier: Programming Language :: Python :: 3.10
Classifier: Programming Language :: Python :: 3.11
Classifier: Programming Language :: Python :: 3.12
Classifier: Topic :: Software Development :: Libraries :: Python Modules
Requires-Python: >=3.9
Requires-Dist: textual>=6.0
Requires-Dist: rich>=14.0
Provides-Extra: dev
Requires-Dist: ruff>=0.6; extra == "dev"
